mysweetpackage/__init__.py
mysweetpackage/module.py
mysweetpackage-0.0.3.dist-info/licenses/LICENSE
mysweetpackage-0.0.3.dist-info/METADATA
mysweetpackage-0.0.3.dist-info/WHEEL
mysweetpackage-0.0.3.dist-info/top_level.txt
mysweetpackage-0.0.3.dist-info/RECORD
