Metadata-Version: 2.4
Name: mysweetpackage
Version: 0.0.3
Summary: Test-driving Python package creation
Home-page: https://github.com/xiandev25/mysweetpackage
Author: CHRISTIAN NGAPGUE
Author-email: xiandev25@gmail.com
License: MIT
Classifier: Programming Language :: Python :: 3
Classifier: License :: OSI Approved :: MIT License
Classifier: Operating System :: OS Independent
Requires-Python: >=3.8
License-File: LICENSE
Dynamic: author
Dynamic: author-email
Dynamic: classifier
Dynamic: description
Dynamic: description-content-type
Dynamic: home-page
Dynamic: license
Dynamic: license-file
Dynamic: requires-python
Dynamic: summary
